README.rst
setup.py
djorm_ext_pgbytea.egg-info/PKG-INFO
djorm_ext_pgbytea.egg-info/SOURCES.txt
djorm_ext_pgbytea.egg-info/dependency_links.txt
djorm_ext_pgbytea.egg-info/not-zip-safe
djorm_ext_pgbytea.egg-info/requires.txt
djorm_ext_pgbytea.egg-info/top_level.txt
djorm_pgbytea/__init__.py
djorm_pgbytea/bytea.py
djorm_pgbytea/compat.py
djorm_pgbytea/fields.py
djorm_pgbytea/lobject.py
tests/__init__.py
tests/settings.py
tests/pg_bytea_fields/__init__.py
tests/pg_bytea_fields/models.py
tests/pg_bytea_fields/tests.py