Metadata-Version: 1.1
Name: djorm-ext-pgbytea
Version: 0.6.0
Summary: Core module of django orm extensions package. Is a collection of third party plugins build in one unified package.
Home-page: https://github.com/niwibe/djorm-ext-pgbytea
Author: Andrey Antukh
Author-email: niwi@niwi.be
License: BSD
Platform: OS Independent
Classifier: Development Status :: 4 - Beta
Classifier: Framework :: Django
Classifier: Intended Audience :: Developers
Classifier: License :: OSI Approved :: BSD License
Classifier: Operating System :: OS Independent
Classifier: Programming Language :: Python
Classifier: Topic :: Internet :: WWW/HTTP
